{
  "project_info": {
    "project_number": "505990540703",
    "project_id": "rephoto-371c9",
    "storage_bucket": "rephoto-371c9.firebasestorage.app"
  },
  "client": [
    {
      "client_info": {
        "mobilesdk_app_id": "1:505990540703:android:4d01af81f3b02a503921aa",
        "android_client_info": {
          "package_name": "com.thezayin.rephoto"
        }
      },
      "oauth_client": [],
      "api_key": [
        {
          "current_key": "AIzaSyBGQnNg0affojD38ExzvrH2LRzOkVGtm64"
        }
      ],
      "services": {
        "appinvite_service": {
          "other_platform_oauth_client": []
        }
      }
    }
  ],
  "configuration_version": "1"
}
